CHANGELOG.rst
CONTRIBUTORS.rst
LICENSE.txt
MANIFEST.in
README.rst
setup.py
cyclope/__init__.py
cyclope/admin.py
cyclope/dashboard.py
cyclope/default_settings.py
cyclope/default_urls.py
cyclope/feeds.py
cyclope/fields.py
cyclope/forms.py
cyclope/frontend_views.py
cyclope/middleware.py
cyclope/models.py
cyclope/registration_backends.py
cyclope/server_global_settings.py
cyclope/settings.py
cyclope/signals.py
cyclope/sitemaps.py
cyclope/test_urls.py
cyclope/tests.py
cyclope/themes.py
cyclope/urls.py
cyclope/views.py
cyclope/widgets.py
cyclope/apps/__init__.py
cyclope/apps/abuse/__init__.py
cyclope/apps/abuse/admin.py
cyclope/apps/abuse/models.py
cyclope/apps/abuse/tests.py
cyclope/apps/abuse/urls.py
cyclope/apps/abuse/views.py
cyclope/apps/abuse/migrations/0001_initial.py
cyclope/apps/abuse/migrations/__init__.py
cyclope/apps/abuse/templates/abuse/abuse_report_email.txt
cyclope/apps/abuse/templates/abuse/report.html
cyclope/apps/abuse/templatetags/__init__.py
cyclope/apps/abuse/templatetags/abuse.py
cyclope/apps/articles/__init__.py
cyclope/apps/articles/admin.py
cyclope/apps/articles/dbgettext_registration.py
cyclope/apps/articles/frontend_views.py
cyclope/apps/articles/models.py
cyclope/apps/articles/search_indexes.py
cyclope/apps/articles/tests.py
cyclope/apps/articles/urls.py
cyclope/apps/articles/migrations/0001_initial.py
cyclope/apps/articles/migrations/0002_auto__del_source__del_author__chg_field_article_author__chg_field_arti.py
cyclope/apps/articles/migrations/0003_auto__add_articleimagedata.py
cyclope/apps/articles/migrations/0004_auto__chg_field_articleimagedata_label.py
cyclope/apps/articles/migrations/0005_del_article__pictures.py
cyclope/apps/articles/migrations/0006_auto__add_field_article_modification_date.py
cyclope/apps/articles/migrations/0007_auto__del_articleimagedata__del_attachment.py
cyclope/apps/articles/migrations/0008_auto__chg_field_article_author__chg_field_article_creation_date.py
cyclope3.egg-info/PKG-INFO
cyclope3.egg-info/SOURCES.txt
cyclope3.egg-info/dependency_links.txt
cyclope3.egg-info/not-zip-safe
cyclope3.egg-info/requires.txt
cyclope3.egg-info/top_level.txt