Metadata-Version: 1.1
Name: cyclope3
Version: 0.4.1.2
Summary: CMS for pythonistas who like to code instead of using a web UI for every task.
Home-page: http://forja.codigosur.org/projects/cyclope/
Author: Santiago Piccinini
Author-email: spiccinini@codigosur.org
License: GPL v3
Platform: OS Independent
Classifier: Development Status :: 5 - Production/Stable
Classifier: Environment :: Web Environment
Classifier: Framework :: Django
Classifier: Intended Audience :: Developers
Classifier: License :: OSI Approved :: GNU General Public License v3 (GPLv3)
Classifier: Operating System :: OS Independent
Classifier: Programming Language :: Python
Classifier: Programming Language :: Python :: 2.6
Classifier: Programming Language :: Python :: 2.7
Classifier: Topic :: Internet :: WWW/HTTP :: Dynamic Content
Classifier: Topic :: Software Development
Classifier: Topic :: Software Development :: Libraries :: Application Frameworks
